{
    "id": "string",
    "version": "string",
    "activeVersion": true,
    "commercialLanguage": "string",
    "commission": "string",
    "commissionSalesPartners": [
      {
        "id": "string",
        "version": "string",
        "commissionFix": "string",
        "commissionPercentage": "string",
        "commissionType": "FIX",
        "createdDate": 0,
        "lastModifiedDate": 0,
        "salesPartnerSupplierId": "string",
        "salesPartnerSupplierNumber": "string"
      }
    ],
    "createdDate": 0,
    "currencyConversionDate": 0,
    "currencyConversionRate": "string",
    "customAttributes": [
      {
        "attributeDefinitionId": "string",
        "booleanValue": true,
        "dateValue": 0,
        "entityId": "string",
        "entityReferences": [
          {
            "entityId": "string",
            "entityName": "string"
          }
        ],
        "numberValue": "string",
        "selectedValueId": "string",
        "selectedValues": [
          {
            "id": "string"
          }
        ],
        "stringValue": "string"
      }
    ],
    "customerId": "string",
    "customerNumber": "string",
    "defaultShippingCarrierId": "string",
    "defaultShippingCarrierName": "string",
    "deliveryAddress": {
      "city": "string",
      "company": "string",
      "company2": "string",
      "countryCode": "string",
      "firstName": "string",
      "globalLocationNumber": "string",
      "lastName": "string",
      "middleName": "string",
      "phoneNumber": "string",
      "postOfficeBoxCity": "string",
      "postOfficeBoxNumber": "string",
      "postOfficeBoxZipCode": "string",
      "salutation": "COMPANY",
      "state": "string",
      "street1": "string",
      "street2": "string",
      "title": "string",
      "titleId": "string",
      "zipcode": "string"
    },
    "deliveryEmailAddresses": {
      "bccAddresses": "string",
      "ccAddresses": "string",
      "toAddresses": "string"
    },
    "description": "string",
    "disableEmailTemplate": true,
    "dispatchCountryCode": "string",
    "factoring": true,
    "grossAmount": "string",
    "grossAmountInCompanyCurrency": "string",
    "headerDiscount": "string",
    "headerSurcharge": "string",
    "invoiceAddress": {
      "city": "string",
      "company": "string",
      "company2": "string",
      "countryCode": "string",
      "firstName": "string",
      "globalLocationNumber": "string",
      "lastName": "string",
      "middleName": "string",
      "phoneNumber": "string",
      "postOfficeBoxCity": "string",
      "postOfficeBoxNumber": "string",
      "postOfficeBoxZipCode": "string",
      "salutation": "COMPANY",
      "state": "string",
      "street1": "string",
      "street2": "string",
      "title": "string",
      "titleId": "string",
      "zipcode": "string"
    },
    "invoiceRecipientId": "string",
    "lastModifiedDate": 0,
    "netAmount": "string",
    "netAmountInCompanyCurrency": "string",
    "nonStandardTaxId": "string",
    "nonStandardTaxName": "string",
    "opportunityId": "string",
    "opportunityNumber": "string",
    "paymentMethodId": "string",
    "paymentMethodName": "string",
    "plannedDeliveryDate": 0,
    "plannedShippingDate": 0,
    "pricingDate": 0,
    "publicLink": "string",
    "quotationDate": 0,
    "quotationItems": [
      {
        "id": "string",
        "version": "string",
        "addPageBreakBefore": true,
        "alternative": true,
        "articleId": "string",
        "articleNumber": "string",
        "commissionSalesPartners": [
          {
            "id": "string",
            "version": "string",
            "commissionFix": "string",
            "commissionPercentage": "string",
            "commissionType": "FIX",
            "createdDate": 0,
            "lastModifiedDate": 0,
            "salesPartnerSupplierId": "string",
            "salesPartnerSupplierNumber": "string"
          }
        ],
        "createdDate": 0,
        "customAttributes": [
          {
            "attributeDefinitionId": "string",
            "booleanValue": true,
            "dateValue": 0,
            "entityId": "string",
            "entityReferences": [
              {
                "entityId": "string",
                "entityName": "string"
              }
            ],
            "numberValue": "string",
            "selectedValueId": "string",
            "selectedValues": [
              {
                "id": "string"
              }
            ],
            "stringValue": "string"
          }
        ],
        "description": "string",
        "descriptionFixed": true,
        "discountPercentage": "string",
        "freeTextItem": true,
        "grossAmount": "string",
        "grossAmountInCompanyCurrency": "string",
        "groupName": "string",
        "invoicingType": "EFFORT",
        "lastModifiedDate": 0,
        "manualPlannedWorkingTimePerUnit": true,
        "manualQuantity": true,
        "manualUnitCost": true,
        "manualUnitPrice": true,
        "netAmount": "string",
        "netAmountForStatistics": "string",
        "netAmountForStatisticsInCompanyCurrency": "string",
        "netAmountInCompanyCurrency": "string",
        "note": "string",
        "optional": true,
        "parentItemId": "string",
        "plannedWorkingTimePerUnit": "string",
        "positionNumber": 0,
        "quantity": "string",
        "reductionAdditionItems": [
          {
            "position": 0,
            "source": "ARTICLE",
            "type": "ADDITION_ABSOLUTE",
            "value": "string"
          }
        ],
        "serviceItem": true,
        "servicePeriodFrom": 0,
        "servicePeriodTo": 0,
        "taxId": "string",
        "taxName": "string",
        "title": "string",
        "unitCost": "string",
        "unitCostInCompanyCurrency": "string",
        "unitId": "string",
        "unitName": "string",
        "unitPrice": "string",
        "unitPriceInCompanyCurrency": "string"
      }
    ],
    "quotationNumber": "string",
    "quotationType": "CONTRACT",
    "quotationVersion": 0,
    "recordAddress": {
      "city": "string",
      "company": "string",
      "company2": "string",
      "countryCode": "string",
      "firstName": "string",
      "globalLocationNumber": "string",
      "lastName": "string",
      "middleName": "string",
      "phoneNumber": "string",
      "postOfficeBoxCity": "string",
      "postOfficeBoxNumber": "string",
      "postOfficeBoxZipCode": "string",
      "salutation": "COMPANY",
      "state": "string",
      "street1": "string",
      "street2": "string",
      "title": "string",
      "titleId": "string",
      "zipcode": "string"
    },
    "recordComment": "string",
    "recordCurrencyId": "string",
    "recordCurrencyName": "string",
    "recordEmailAddresses": {
      "bccAddresses": "string",
      "ccAddresses": "string",
      "toAddresses": "string"
    },
    "recordFreeText": "string",
    "recordOpening": "string",
    "rejectionReason": "string",
    "requestDate": 0,
    "responsibleUserId": "string",
    "responsibleUserUsername": "string",
    "salesChannel": "string",
    "salesInvoiceEmailAddresses": {
      "bccAddresses": "string",
      "ccAddresses": "string",
      "toAddresses": "string"
    },
    "salesOrderEmailAddresses": {
      "bccAddresses": "string",
      "ccAddresses": "string",
      "toAddresses": "string"
    },
    "salesProbability": 0,
    "salesStageHistory": [
      {
        "id": "string",
        "version": "string",
        "createdDate": 0,
        "lastModifiedDate": 0,
        "salesStageId": "string",
        "salesStageName": "string",
        "userId": "string"
      }
    ],
    "salesStageId": "string",
    "salesStageName": "string",
    "sentToRecipient": true,
    "servicePeriodFrom": 0,
    "servicePeriodTo": 0,
    "shipmentMethodId": "string",
    "shipmentMethodName": "string",
    "shippingCostItems": [
      {
        "id": "string",
        "version": "string",
        "articleId": "string",
        "articleNumber": "string",
        "createdDate": 0,
        "grossAmount": "string",
        "grossAmountInCompanyCurrency": "string",
        "lastModifiedDate": 0,
        "manualUnitCost": true,
        "manualUnitPrice": true,
        "netAmount": "string",
        "netAmountInCompanyCurrency": "string",
        "taxId": "string",
        "taxName": "string",
        "unitCost": "string",
        "unitCostInCompanyCurrency": "string",
        "unitPrice": "string",
        "unitPriceInCompanyCurrency": "string"
      }
    ],
    "status": "ACCEPTED",
    "statusHistory": [
      {
        "status": "ACCEPTED",
        "statusDate": 0,
        "userId": "string"
      }
    ],
    "tags": [
      "string"
    ],
    "template": true,
    "termOfPaymentId": "string",
    "termOfPaymentName": "string",
    "validFrom": 0,
    "validTo": 0,
    "warehouseId": "string",
    "warehouseName": "string"
  }